setup.py
django_s3_direct_view.egg-info/PKG-INFO
django_s3_direct_view.egg-info/SOURCES.txt
django_s3_direct_view.egg-info/dependency_links.txt
django_s3_direct_view.egg-info/requires.txt
django_s3_direct_view.egg-info/top_level.txt
s3_direct/__init__.py
s3_direct/s3.py
s3_direct/serializers.py
s3_direct/settings.py
s3_direct/views.py