Metadata-Version: 1.1
Name: django-s3-direct-view
Version: 0.1.0
Summary: Util for DRF param generation for s3 direct upload
Home-page: https://github.com/pypa/sampleproject
Author: Saritasa
Author-email: andrey.potekhin@saritasa.com
License: UNKNOWN
Keywords: django drf s3
Platform: UNKNOWN
Classifier: Programming Language :: Python :: 2
Classifier: Programming Language :: Python :: 2.7
Classifier: Programming Language :: Python :: 3
Classifier: Programming Language :: Python :: 3.4
Classifier: Programming Language :: Python :: 3.5
Classifier: Programming Language :: Python :: 3.6
